README.rst
emitjson.py
setup.py
emitjson.egg-info/PKG-INFO
emitjson.egg-info/SOURCES.txt
emitjson.egg-info/dependency_links.txt
emitjson.egg-info/top_level.txt