Metadata-Version: 1.1
Name: emitjson
Version: 0.0.4
Summary: Help composing objects to build JSON.
Home-page: https://github.com/atsuoishimoto/emitjson
Author: Atsuo Ishimoto
Author-email: UNKNOWN
License: MIT
Keywords: json
Platform: UNKNOWN
Classifier: Programming Language :: Python :: 3.4
Classifier: Development Status :: 5 - Production/Stable
Classifier: License :: OSI Approved :: MIT License
Classifier: Topic :: Software Development :: Libraries :: Python Modules
